{
  "faq": [
    {
      "pergunta": "Qual é o tipo de lona?",
      "resp": "A mais resistente do mercado, 440g de espessura, 2 anos de garantia."
    },
    {
      "pergunta": "Vocês fazem a arte e imprimem?",
      "resp": "Sim, desde a visita técnica ou negociação virtual, até sua arte e material instalado."
    },
    {
      "pergunta": "Será que vou gostar da arte?",
      "resp": "Só vamos imprimir seu material depois de sua autorização, a arte está aberta a modificações e sugestões."
    }
  ]
}
